#################### main-page ############
<Window text = "Test VApp" rect = "0 0 800 600" style="popup sys-menu min-box" bgcolor="#FFB6C1" bgimage="b.bmp stretch" padding="1 1 1 1" border="solid 1px #3A5FCD" >
	<default class="Button" normalImage="ext_button.bmp [0 48 75 24] 9patch" hoverImage="ext_button.bmp [0 24 75 24] 9patch" pushImage="ext_button.bmp [0 0 75 24] 9patch" />
	<default class="VerScrollBar" rect="0 0 15 100%" track="color://#99aabbcc" thumb="color://#ffbbcc" />
	<default class="HorScrollBar" rect="0 0 100% 15" track="color://#99aabbcc" thumb="color://#ffbbcc" />
	<default class="Radio" normalImage="radio_normal.png" hoverImage="radio_normal.png" pushImage="radio_normal.png" selectImage="radio_select.png" />
	<default class="ComboBox_List" bgcolor="#30fab85a" />
	
	<WindowBar rect="0 0 100% 35" bgimage="color://#80F0E68C" />
	
	<Button id="ext_btn_1" rect="20 20 100 25" text="A Button" />
	
	<ComboBox id="combo" rect="100 100 150 25" bgcolor="#50ddccdd" arrowNormal="ext_combobox_arrow_normal.png stretch" arrowPush="ext_combobox_arrow_down.png stretch" />
	
</Window>

#################### my-popup ############
<Popup rect="220 50 300 200" bgcolor="#50fab85a" >
	
</Popup>

#################### my-popmenu ############
<PopupMenu font="size:14;">
	
</PopupMenu>

#################### my-tree ############
<TreeNode>
	<TreeNode text="San tai hu" >
		<TreeNode text="Flip"  />
	</TreeNode>
	<TreeNode text="Bai Du" expand="true">
		<TreeNode text="Good" checkable="true"  />
		<TreeNode text="Bad"  checkable="true" checked="true">
			<TreeNode text="真不懂" />
			<TreeNode text="好的" />
		</TreeNode>
	</TreeNode>
	<TreeNode text="My Fav" >
		<TreeNode text="Simple" />
		<TreeNode text="Many" >
			<TreeNode text="Many A" />
			<TreeNode text="Many B" />
			<TreeNode text="Many C" />
		</TreeNode>
		<TreeNode text="Love" >
			<TreeNode text="Love Me" />
			<TreeNode text="Love You" />
			<TreeNode text="Love She" />
		</TreeNode>
	</TreeNode>
</TreeNode>

#################### my-menu ############
<MenuItem>
	<MenuItem name="A" text="AAAAA"    />
	<MenuItem name="B" text="BBBBBB"   />
	<MenuItem separator="true"  />
	<MenuItem name="C" text="姓别"  >
		<MenuItem name="C1" text="男" checkable="true"  />
		<MenuItem  name="C2" text="女" checkable="true" >
			<MenuItem name="A1" text="Old Woman"    />
			<MenuItem name="B1" text="Yong Woman"   />
		</MenuItem>
	</MenuItem>
	<MenuItem separator="true"  />
	<MenuItem name="D" text="DDDD"   />
</MenuItem>
